forgerequestlog/__init__.py
forgerequestlog/core.py
forgerequestlog/middleware.py
forgerequestlog/settings.py
forgerequestlog/templates/requestlog/requestlog.html
forgerequestlog/templates/requestlog/stafftoolbar.html
forgerequestlog/views.py
forge_requestlog-0.2.0.dist-info/METADATA
forge_requestlog-0.2.0.dist-info/WHEEL
forge_requestlog-0.2.0.dist-info/RECORD
